foodWebsAnalyzer/__init__.py
foodWebsAnalyzer/foodWebsAnalyzer.py
foodWebsAnalyzer/common/__init__.py
foodWebsAnalyzer/common/inputParameters.py
foodWebsAnalyzer/common/matrixOperations.py
foodWebsAnalyzer/common/printer.py
foodWebsAnalyzer/ecosystems/__init__.py
foodWebsAnalyzer/ecosystems/balancing.py
foodWebsAnalyzer/ecosystems/ecosystem.py
foodWebsAnalyzer/ecosystems/proportions.py
foodWebsAnalyzer/ecosystems/analysis/__init__.py
foodWebsAnalyzer/ecosystems/analysis/donorControlModel.py
foodWebsAnalyzer/ecosystems/analysis/generalModel.py
foodWebsAnalyzer/ecosystems/analysis/stability.py
foodWebsAnalyzer/ecosystems/analysis/steadyStates.py
foodWebsAnalyzer/ecosystems/controlSpaces/__init__.py
foodWebsAnalyzer/ecosystems/controlSpaces/controlSpaceJacobian.py
foodWebsAnalyzer/ecosystems/data/__init__.py
foodWebsAnalyzer/ecosystems/data/foodWebData.py
foodWebsAnalyzer/ecosystems/data/symbolicData.py
foodWebsAnalyzer/ecosystems/ode/__init__.py
foodWebsAnalyzer/ecosystems/ode/odeChecker.py
foodWebsAnalyzer/ecosystems/ode/odeSolver.py
foodWebsAnalyzer/utils/__init__.py
foodWebsAnalyzer/utils/ode.py
foodWebsAnalyzer/utils/testFunctions.py
foodWebsAnalyzer/utils/transform.py
food_webs_analyzer-0.1.dist-info/METADATA
food_webs_analyzer-0.1.dist-info/WHEEL
food_webs_analyzer-0.1.dist-info/top_level.txt
food_webs_analyzer-0.1.dist-info/RECORD
